django_auto_listview/__init__.py
django_auto_listview/admin.py
django_auto_listview/apps.py
django_auto_listview/models.py
django_auto_listview/urls.py
django_auto_listview/views.py
django_auto_listview/__pycache__/__init__.cpython-310.pyc
django_auto_listview/__pycache__/admin.cpython-310.pyc
django_auto_listview/__pycache__/apps.cpython-310.pyc
django_auto_listview/__pycache__/models.cpython-310.pyc
tests/__init__.py
tests/test_app.py
django_auto_listview-0.1.0.dist-info/LICENSE
django_auto_listview-0.1.0.dist-info/METADATA
django_auto_listview-0.1.0.dist-info/WHEEL
django_auto_listview-0.1.0.dist-info/top_level.txt
django_auto_listview-0.1.0.dist-info/RECORD
