Metadata-Version: 2.1
Name: django-auto-listview
Version: 0.1.0
Summary: A Django app for dynamic admin list views.
Home-page: https://github.com/smbd1368/django-auto-listview
Author: Mohamad Bagher Davoodi
Author-email: mohamadbagherdavoodi@gmail.com
Classifier: Framework :: Django
Classifier: Programming Language :: Python :: 3
Classifier: License :: OSI Approved :: MIT License
Classifier: Operating System :: OS Independent
License-File: LICENSE
Requires-Dist: django>=3.2
